examples/checks.yaml
examples/checks2.yaml
propertree/__init__.py
propertree/log.py
propertree/propertree2.py
propertree-2.1.dist-info/licenses/LICENSE
tests/__init__.py
tests/unit/__init__.py
tests/unit/properties.py
tests/unit/test_ptree.py
tests/unit/test_ptree2.py
tests/unit/test_ptree_basic.py
tests/unit/test_ptree_mapped_properties.py
tests/unit/utils.py
propertree-2.1.dist-info/METADATA
propertree-2.1.dist-info/WHEEL
propertree-2.1.dist-info/top_level.txt
propertree-2.1.dist-info/RECORD
