Metadata-Version: 2.4
Name: propertree
Version: 2.1
Summary: Library to help create meaningful structures from yaml or json.
Requires-Python: >=3.8
License-File: LICENSE
Requires-Dist: importlib-metadata; python_version >= "3.8"
Dynamic: license-file
